{"fecha":"2020-07-31","publicaciones":"2","videos":"3","horas":"03:00","revisitas":"3","estudios":"2","id":2}
{"fecha":"2020-08-01","publicaciones":"1","videos":"1","horas":"01:00","revisitas":"1","estudios":"1","id":3}
{"id":"19","fecha":"2020-08-01","publicaciones":"1","videos":"1","horas":"01:00","revisitas":"1","estudios":"1"}
{"fecha":"2020-08-02","publicaciones":"1","videos":"1","horas":"02:00","revisitas":"3","estudios":"3","id":21}
{"fecha":"2020-08-05","publicaciones":0,"videos":0,"horas":"00:30","revisitas":0,"estudios":0,"id":22}
